dhapackage/__init__.py
dhapackage/greet.py
dhapackage-0.1.dist-info/METADATA
dhapackage-0.1.dist-info/WHEEL
dhapackage-0.1.dist-info/top_level.txt
dhapackage-0.1.dist-info/RECORD
